[
  {
    "videosrc": "//pic4.iqiyipic.com/image/20220508/0b/29/a_100498863_m_601_zh-TW_m3_260_360.webp",
    "videoname": "Shooting Stars流星",
    "videodetaillink": "//www.iq.com/play/shooting-stars%E6%B5%81%E6%98%9F-%E7%AC%AC1%E9%9B%86-ac1fmaxd5w?lang=zh_tw",
    "previewpic": [
      "//pic8.iqiyipic.com/image/20220501/a8/ad/v_166609714_m_601_zh-TW_m1_220_124.jpg",
      "//pic6.iqiyipic.com/image/20220501/68/38/v_167180661_m_601_zh-TW_m1_220_124.jpg",
      "//pic4.iqiyipic.com/image/20220501/21/04/v_167228778_m_601_zh-TW_m1_220_124.jpg",
      "//pic0.iqiyipic.com/image/20220501/4d/20/v_167228820_m_601_zh-TW_220_124.jpg",
      "//pic0.iqiyipic.com/image/20220507/37/20/v_167358923_m_601_zh-TW_220_124.jpg",
      "//pic5.iqiyipic.com/image/20220508/bf/55/v_167373932_m_601_zh-TW_220_124.jpg",
      "//pic0.iqiyipic.com/image/20220514/af/d1/v_167462419_m_601_zh-TW_m1_220_124.jpg",
      "//pic2.iqiyipic.com/image/20220514/ce/e8/v_167458416_m_601_zh-TW_m1_220_124.jpg"
    ],
    "previewname": [
      "Shooting Stars流星 第1集",
      "Shooting Stars流星 第2集",
      "Shooting Stars流星 第3集",
      "Shooting Stars流星 第4集",
      "Shooting Stars流星 第5集",
      "Shooting Stars流星 第6集",
      "Shooting Stars流星 第7集",
      "Shooting Stars流星 第8集"
    ],
    "actoricon": [
      "(//pic2.iqiyipic.com/image/20210713/fd/17/p_5305529_m_601_300_300.jpg)",
      "(//pic4.iqiyipic.com/image/20220501/9d/11/p_5131067_m_601_m6_300_300.jpg)",
      "(//pic0.iqiyipic.com/image/20220501/99/bc/p_5299039_m_601_m2_300_300.jpg)",
      "(//pic7.iqiyipic.com/image/20220501/e9/cc/p_2014908_m_601_m7_300_300.jpg)",
      "(//pic7.iqiyipic.com/image/20220501/87/4d/p_2008400_m_601_m4_300_300.jpg)",
      "(//pic3.iqiyipic.com/image/20220501/b6/21/p_5060209_m_601_m5_300_300.jpg)",
      "(//pic9.iqiyipic.com/image/20220501/4f/0b/p_2013105_m_601_m4_300_300.jpg)",
      "(//pic6.iqiyipic.com/image/20220501/54/ff/p_5263337_m_601_m2_300_300.jpg)",
      "(//pic4.iqiyipic.com/image/20220303/46/00/p_5305570_m_601_m1_300_300.jpg)"
    ],
    "actorname": [
      "李秀賢",
      "李聖經",
      "金永大",
      "尹鐘焄",
      "金允慧",
      "素珍",
      "李正信",
      "李承協",
      "河道權"
    ],
    "videoyear": "2022",
    "videoallepisodes": "更新至7集/共16集",
    "videoscore": "9.8",
    "videotype": "愛情 ，劇情  ，喜劇  ",
    "videodiscribtion": "韓劇《Shooting Stars流星》(2022)講述以身居明星管理最前線的經紀公關組長吳寒星與他的天敵兼完美無缺的頂級明星孔泰成之間的糾葛和成長故事。 該劇講述為了演藝圈的亮眼明星們，跟在後面收拾殘局的各類辛苦人們，站在照顧藝人的最前線，經紀公司公關組長吳寒星（李聖經飾）以及她的天敵，也就是完美無缺的超級巨星孔泰成（金永大飾），是一部愛恨交織的浪漫愛情喜劇。 一個精明能幹的經紀公司公關組長，培養著公司的招牌男偶像明星，兩人會如何擦出火花？ 《Shooting Stars流星》由李聖經(《浪漫醫生金師傅2》、《舉重妖精金福珠》)、金永大(《Penthouse上流戰爭》、《無意間發現的一天》)主演，線上看由愛奇藝國際站及iQIYI APP播出。"
  },
  {
    "videosrc": "//pic4.iqiyipic.com/image/20220315/65/14/a_100489191_m_601_zh-TW_m4_260_360.webp",
    "videoname": "解讀惡之心的人們",
    "videodetaillink": "//www.iq.com/play/%E8%A7%A3%E8%AE%80%E6%83%A1%E4%B9%8B%E5%BF%83%E7%9A%84%E4%BA%BA%E5%80%91-%E7%AC%AC1%E9%9B%86-1ae6iua2al4?lang=zh_tw"
  },
  {
    "videosrc": "//pic6.iqiyipic.com/image/20220126/ec/1b/a_100484196_m_601_zh-TW_m24_260_360.webp",
    "videoname": "Bad and Crazy邪惡與瘋狂",
    "videodetaillink": "//www.iq.com/play/bad-and-crazy%E9%82%AA%E6%83%A1%E8%88%87%E7%98%8B%E7%8B%82-%E7%AC%AC1%E9%9B%86-1fj6iypksgg?lang=zh_tw"
  },
  {
    "videosrc": "//pic3.iqiyipic.com/image/20210907/6d/58/a_100463035_m_601_zh-TW_m2_260_360.webp",
    "videoname": "優秀巫師賈斗心",
    "videodetaillink": "//www.iq.com/play/%E5%84%AA%E7%A7%80%E5%B7%AB%E5%B8%AB%E8%B3%88%E6%96%97%E5%BF%83-%E7%AC%AC1%E9%9B%86-hzb9aeqdog?lang=zh_tw"
  },
  {
    "videosrc": "//pic9.iqiyipic.com/image/20211011/b7/27/a_100399666_m_601_zh-TW_m4_260_360.webp",
    "videoname": "法外搜查",
    "videodetaillink": "//www.iq.com/play/%E6%B3%95%E5%A4%96%E6%90%9C%E6%9F%A5-%E7%AC%AC1%E9%9B%86-19rxvcs4wc?lang=zh_tw"
  },
  {
    "videosrc": "//pic2.iqiyipic.com/image/20211015/4e/94/a_100475125_m_601_zh-TW_m2_260_360.webp",
    "videoname": "One The Woman雙重人生",
    "videodetaillink": "//www.iq.com/play/one-the-woman%E9%9B%99%E9%87%8D%E4%BA%BA%E7%94%9F-%E7%AC%AC1%E9%9B%86-26ecr2qrt1c?lang=zh_tw"
  },
  {
    "videosrc": "//pic1.iqiyipic.com/image/20200419/a7/e0/a_100394134_m_601_m1_260_360.webp",
    "videoname": "重生Born Again",
    "videodetaillink": "//www.iq.com/play/%E9%87%8D%E7%94%9Fborn-again-%E7%AC%AC1%E9%9B%86-19rykaqqng?lang=zh_tw"
  },
  {
    "videosrc": "//pic4.iqiyipic.com/image/20210525/58/2d/a_100450216_m_601_zh-TW_m6_260_360.webp",
    "videoname": "大發不動產",
    "videodetaillink": "//www.iq.com/play/%E5%A4%A7%E7%99%BC%E4%B8%8D%E5%8B%95%E7%94%A2-%E7%AC%AC1%E9%9B%86-1kaxulzryw8?lang=zh_tw"
  },
  {
    "videosrc": "//pic0.iqiyipic.com/image/20201023/fa/0c/a_100429243_m_601_zh-TW_m1_260_360.webp",
    "videoname": "Penthouse上流戰爭(上流社會) 第一季",
    "videodetaillink": "//www.iq.com/play/penthouse%E4%B8%8A%E6%B5%81%E6%88%B0%E7%88%AD-%E4%B8%8A%E6%B5%81%E7%A4%BE%E6%9C%83-%E7%AC%AC%E4%B8%80%E5%AD%A3-%E7%AC%AC1%E9%9B%86-1tehnwaee7s?lang=zh_tw"
  },
  {
    "videosrc": "//pic8.iqiyipic.com/image/20210718/a4/5c/a_100452511_m_601_zh-TW_m5_260_360.webp",
    "videoname": "我的室友是九尾狐",
    "videodetaillink": "//www.iq.com/play/%E6%88%91%E7%9A%84%E5%AE%A4%E5%8F%8B%E6%98%AF%E4%B9%9D%E5%B0%BE%E7%8B%90-%E7%AC%AC1%E9%9B%86-novsoqbl8g?lang=zh_tw"
  },
  {
    "videosrc": "//pic5.iqiyipic.com/image/20210630/65/38/a_100455193_m_601_zh-TW_m7_260_360.webp",
    "videoname": "某一天滅亡來到我家門前",
    "videodetaillink": "//www.iq.com/play/%E6%9F%90%E4%B8%80%E5%A4%A9%E6%BB%85%E4%BA%A1%E4%BE%86%E5%88%B0%E6%88%91%E5%AE%B6%E9%96%80%E5%89%8D-%E7%AC%AC1%E9%9B%86-1ucqqty5pyo?lang=zh_tw"
  },
  {
    "videosrc": "//pic7.iqiyipic.com/image/20210915/ba/ea/a_100475692_m_601_zh-TW_m1_260_360.webp",
    "videoname": "達利和馬鈴薯湯",
    "videodetaillink": "//www.iq.com/play/%E9%81%94%E5%88%A9%E5%92%8C%E9%A6%AC%E9%88%B4%E8%96%AF%E6%B9%AF-%E7%AC%AC1%E9%9B%86-glvldw5sec?lang=zh_tw"
  },
  {
    "videosrc": "//pic2.iqiyipic.com/image/20211004/e4/64/a_100469186_m_601_zh-TW_m3_260_360.webp",
    "videoname": "柔美的細胞小將",
    "videodetaillink": "//www.iq.com/play/%E6%9F%94%E7%BE%8E%E7%9A%84%E7%B4%B0%E8%83%9E%E5%B0%8F%E5%B0%87-%E7%AC%AC1%E9%9B%86-1we072tq5io?lang=zh_tw"
  },
  {
    "videosrc": "//pic0.iqiyipic.com/image/20211125/e2/c8/a_100479079_m_601_zh-TW_m3_260_360.webp",
    "videoname": "酒鬼都市女人們",
    "videodetaillink": "//www.iq.com/play/%E9%85%92%E9%AC%BC%E9%83%BD%E5%B8%82%E5%A5%B3%E4%BA%BA%E5%80%91-%E7%AC%AC1%E9%9B%86-1gwvv7o2b1s?lang=zh_tw"
  },
  {
    "videosrc": "//pic4.iqiyipic.com/image/20211011/54/08/a_100420134_m_601_zh-TW_m24_260_360.webp",
    "videoname": "九尾狐傳",
    "videodetaillink": "//www.iq.com/play/%E4%B9%9D%E5%B0%BE%E7%8B%90%E5%82%B3-%E7%AC%AC1%E9%9B%86-1u9rlraym0w?lang=zh_tw"
  },
  {
    "videosrc": "//pic9.iqiyipic.com/image/20201128/90/25/a_100419018_m_601_zh-TW_m5_260_360.webp",
    "videoname": "重返18歲",
    "videodetaillink": "//www.iq.com/play/%E9%87%8D%E8%BF%9418%E6%AD%B2-%E7%AC%AC1%E9%9B%86-1cul7zi4jzo?lang=zh_tw"
  },
  {
    "videosrc": "//pic8.iqiyipic.com/image/20210621/30/df/a_100451604_m_601_zh-TW_m9_260_360.webp",
    "videoname": "所以我和黑粉結婚了",
    "videodetaillink": "//www.iq.com/play/%E6%89%80%E4%BB%A5%E6%88%91%E5%92%8C%E9%BB%91%E7%B2%89%E7%B5%90%E5%A9%9A%E4%BA%86-%E7%AC%AC1%E9%9B%86-2bq1g9xaa0o?lang=zh_tw"
  },
  {
    "videosrc": "//pic7.iqiyipic.com/image/20211208/03/ab/a_100480029_m_601_zh-TW_m10_260_360.webp",
    "videoname": "Happiness毒樓",
    "videodetaillink": "//www.iq.com/play/happiness%E6%AF%92%E6%A8%93-%E7%AC%AC1%E9%9B%86-1jcgfmjm9d4?lang=zh_tw"
  },
  {
    "videosrc": "//pic0.iqiyipic.com/image/20210724/ee/38/a_100387611_m_601_zh-TW_m4_260_360.webp",
    "videoname": "快過來",
    "videodetaillink": "//www.iq.com/play/%E5%BF%AB%E9%81%8E%E4%BE%86-%E7%AC%AC1%E9%9B%86-19rx09bc78?lang=zh_tw"
  },
  {
    "videosrc": "//pic2.iqiyipic.com/image/20220218/cc/b8/a_100390600_m_601_zh-TW_m10_260_360.webp",
    "videoname": "夫婦的世界(夫妻的世界)",
    "videodetaillink": "//www.iq.com/play/%E5%A4%AB%E5%A9%A6%E7%9A%84%E4%B8%96%E7%95%8C-%E5%A4%AB%E5%A6%BB%E7%9A%84%E4%B8%96%E7%95%8C-%E7%AC%AC1%E9%9B%86-19rx0gcasg?lang=zh_tw"
  }
]